doconce_publish-1.1.1.data/data/share/man/man1/publish.1.gz
doconce_publish-1.1.1.data/scripts/publish
publish/__init__.py
publish/algorithms.py
publish/common.py
publish/database.py
publish/exceptions.py
publish/exporting.py
publish/filtering.py
publish/importing.py
publish/interaction.py
publish/keygeneration.py
publish/log.py
publish/merging.py
publish/printing.py
publish/validation.py
publish/config/__init__.py
publish/config/defaults.py
publish/config/formatting.py
publish/formats/__init__.py
publish/formats/bibtex.py
publish/formats/graphml.py
publish/formats/html.py
publish/formats/latex.py
publish/formats/pdf.py
publish/formats/pub.py
publish/formats/rst.py
doconce_publish-1.1.1.dist-info/COPYING
doconce_publish-1.1.1.dist-info/LICENSE
doconce_publish-1.1.1.dist-info/METADATA
doconce_publish-1.1.1.dist-info/WHEEL
doconce_publish-1.1.1.dist-info/top_level.txt
doconce_publish-1.1.1.dist-info/RECORD
